scorejapangarbage.py
scorejapangarbage-1.0.0.dist-info/METADATA
scorejapangarbage-1.0.0.dist-info/WHEEL
scorejapangarbage-1.0.0.dist-info/entry_points.txt
scorejapangarbage-1.0.0.dist-info/top_level.txt
scorejapangarbage-1.0.0.dist-info/RECORD
