Metadata-Version: 2.1
Name: scorejapangarbage
Version: 1.0.0
Summary: UNKNOWN
Home-page: https://github.com/MinamiKota/scorejapangarbage
Author: kota minami
Author-email: s1922076@stu.musashino-u.ac.jp
License: UNKNOWN
Project-URL: Bug Tracker, https://github.com/MinamiKota/scorejapangarbage
Platform: UNKNOWN
Classifier: Programming Language :: Python :: 3
Classifier: License :: OSI Approved :: MIT License
Classifier: Operating System :: OS Independent
Requires-Python: >=3.6
